[
    {
        "german": "aufstehen",
        "english": "to get up",
        "level": "A1",
        "example": "Ich stehe um 7 Uhr auf.",
        "word": "aufstehen",
        "rule": "Separable verb: ich stehe ... auf.",
        "type": "verb",
        "category": "Alltag",
        "id": "verb_alltag_01"
    },
    {
        "german": "essen",
        "english": "to eat",
        "level": "A1",
        "example": "Ich esse gern Pizza.",
        "word": "essen",
        "rule": "Irregular verb: du isst, er isst.",
        "type": "verb",
        "category": "Alltag",
        "id": "verb_alltag_02"
    },
    {
        "german": "trinken",
        "english": "to drink",
        "level": "A1",
        "example": "Ich trinke Wasser.",
        "word": "trinken",
        "rule": "Regular verb.",
        "type": "verb",
        "category": "Alltag",
        "id": "verb_alltag_03"
    },
    {
        "german": "lesen",
        "english": "to read",
        "level": "A1",
        "example": "Ich lese die Zeitung.",
        "word": "lesen",
        "rule": "Irregular verb: du liest, er liest.",
        "type": "verb",
        "category": "Alltag",
        "id": "verb_alltag_04"
    },
    {
        "german": "schlafen",
        "english": "to sleep",
        "level": "A1",
        "example": "Ich schlafe acht Stunden.",
        "word": "schlafen",
        "rule": "Irregular verb: du schläfst, er schläft.",
        "type": "verb",
        "category": "Alltag",
        "id": "verb_alltag_05"
    },
    {
        "german": "arbeiten",
        "english": "to work",
        "level": "A1",
        "example": "Ich arbeite im Büro.",
        "word": "arbeiten",
        "rule": "Regular verb with extra 'e' in 'du arbeitest'.",
        "type": "verb",
        "category": "Alltag",
        "id": "verb_alltag_06"
    },
    {
        "german": "lernen",
        "english": "to learn",
        "level": "A1",
        "example": "Ich lerne Deutsch.",
        "word": "lernen",
        "rule": "Regular verb.",
        "type": "verb",
        "category": "Alltag",
        "id": "verb_alltag_07"
    },
    {
        "german": "fahren",
        "english": "to drive",
        "level": "A1",
        "example": "Ich fahre zur Arbeit.",
        "word": "fahren",
        "rule": "Irregular verb: du fährst, er fährt.",
        "type": "verb",
        "category": "Alltag",
        "id": "verb_alltag_08"
    },
    {
        "german": "gehen",
        "english": "to go",
        "level": "A1",
        "example": "Ich gehe nach Hause.",
        "word": "gehen",
        "rule": "Irregular verb: ging (Präteritum), gegangen (Perfekt).",
        "type": "verb",
        "category": "Alltag",
        "id": "verb_alltag_09"
    },
    {
        "german": "sehen",
        "english": "to see",
        "level": "A1",
        "example": "Ich sehe einen Film.",
        "word": "sehen",
        "rule": "Irregular verb: du siehst, er sieht.",
        "type": "verb",
        "category": "Alltag",
        "id": "verb_alltag_10"
    },
    {
        "german": "hören",
        "english": "to hear",
        "level": "A1",
        "example": "Ich höre Musik.",
        "word": "hören",
        "rule": "Regular verb.",
        "type": "verb",
        "category": "Alltag",
        "id": "verb_alltag_11"
    },
    {
        "german": "telefonieren",
        "english": "to make a phone call",
        "level": "A1",
        "example": "Ich telefoniere mit meiner Mutter.",
        "word": "telefonieren",
        "rule": "Regular verb, often with 'mit + Dativ'.",
        "type": "verb",
        "category": "Alltag",
        "id": "verb_alltag_12"
    },
    {
        "german": "putzen",
        "english": "to clean",
        "level": "A1",
        "example": "Ich putze die Wohnung.",
        "word": "putzen",
        "rule": "Regular verb.",
        "type": "verb",
        "category": "Alltag",
        "id": "verb_alltag_13"
    },
    {
        "german": "kochen",
        "english": "to cook",
        "level": "A1",
        "example": "Ich koche Pasta.",
        "word": "kochen",
        "rule": "Regular verb.",
        "type": "verb",
        "category": "Alltag",
        "id": "verb_alltag_14"
    },
    {
        "german": "machen",
        "english": "to do/make",
        "level": "A1",
        "example": "Ich mache meine Hausaufgaben.",
        "word": "machen",
        "rule": "Very common regular verb.",
        "type": "verb",
        "category": "Alltag",
        "id": "verb_alltag_15"
    },
    {
        "german": "anrufen",
        "english": "to call (on the phone)",
        "level": "A1",
        "example": "Ich rufe meinen Freund an.",
        "word": "anrufen",
        "rule": "Separable verb: ich rufe ... an.",
        "type": "verb",
        "category": "Alltag",
        "id": "verb_alltag_16"
    },
    {
        "german": "fernsehen",
        "english": "to watch TV",
        "level": "A1",
        "example": "Ich sehe am Abend fern.",
        "word": "fernsehen",
        "rule": "Separable verb: ich sehe ... fern.",
        "type": "verb",
        "category": "Alltag",
        "id": "verb_alltag_17"
    },
    {
        "german": "aufmachen",
        "english": "to open",
        "level": "A1",
        "example": "Ich mache die Tür auf.",
        "word": "aufmachen",
        "rule": "Separable verb: ich mache ... auf.",
        "type": "verb",
        "category": "Alltag",
        "id": "verb_alltag_18"
    },
    {
        "german": "zumachen",
        "english": "to close",
        "level": "A1",
        "example": "Ich mache das Fenster zu.",
        "word": "zumachen",
        "rule": "Separable verb: ich mache ... zu.",
        "type": "verb",
        "category": "Alltag",
        "id": "verb_alltag_19"
    },
    {
        "german": "spielen",
        "english": "to play",
        "level": "A1",
        "example": "Ich spiele gern Fußball.",
        "word": "spielen",
        "rule": "Regular verb.",
        "type": "verb",
        "category": "Alltag",
        "id": "verb_alltag_20"
    }
]